MANIFEST.in
README.rst
setup.py
contact/__init__.py
contact/admin.py
contact/context_processors.py
contact/forms.py
contact/models.py
contact/migrations/0001_initial.py
contact/migrations/__init__.py
contact/templates/contact/index.html
farm_contact.egg-info/PKG-INFO
farm_contact.egg-info/SOURCES.txt
farm_contact.egg-info/dependency_links.txt
farm_contact.egg-info/not-zip-safe
farm_contact.egg-info/top_level.txt