Metadata-Version: 1.1
Name: farm-contact
Version: 0.9
Summary: Provides an enquiry form
Home-page: UNKNOWN
Author: Jon Atkinson
Author-email: jon@wearefarm.com
License: BSD
Keywords: contact
Platform: UNKNOWN
Classifier: Development Status :: 4 - Beta
Classifier: Environment :: Web Environment
Classifier: Framework :: Django
Classifier: Intended Audience :: Developers
Classifier: License :: OSI Approved :: BSD License
Classifier: Operating System :: OS Independent
Classifier: Programming Language :: Python
